{
  "epochs": 6,
  "test_years": [
    2013,
    2014,
    2015,
    2016
  ],
  "scheme": "expanding train, prior year as val; note: year effect confounded with train size",
  "smoke": false,
  "models": {
    "naive": {
      "folds": {
        "2013": {
          "rmse": 3.1624741971021213
        },
        "2014": {
          "rmse": 3.167062944388708
        },
        "2015": {
          "rmse": 3.591396531489006
        },
        "2016": {
          "rmse": 3.214942038823542
        }
      },
      "rmse_mean": 3.2839689279508444,
      "rmse_std": 0.17867877703888355
    },
    "lstm": {
      "folds": {
        "2013": {
          "rmse": 2.583479341804105
        },
        "2014": {
          "rmse": 2.610313599382885
        },
        "2015": {
          "rmse": 2.9349594106356274
        },
        "2016": {
          "rmse": 2.445720987991123
        }
      },
      "rmse_mean": 2.6436183349534352,
      "rmse_std": 0.17942190935252175
    },
    "qlstm": {
      "folds": {
        "2013": {
          "rmse": 2.5782440408615033,
          "crps": 1.1304892730747824,
          "picp": 0.9264432029795159
        },
        "2014": {
          "rmse": 2.596045141542362,
          "crps": 1.1251406754021043,
          "picp": 0.910963687150838
        },
        "2015": {
          "rmse": 2.8490925100800304,
          "crps": 1.2222183447674138,
          "picp": 0.8891992551210428
        },
        "2016": {
          "rmse": 2.4262464515715507,
          "crps": 1.0299942109516143,
          "picp": 0.9186397400185701
        }
      },
      "rmse_mean": 2.6124070360138614,
      "rmse_std": 0.15174863974868635
    },
    "qt": {
      "folds": {
        "2013": {
          "rmse": 2.5735629085758003,
          "crps": 1.0955987316618547,
          "picp": 0.9175977653631285
        },
        "2014": {
          "rmse": 2.56130414540765,
          "crps": 1.0949147478944468,
          "picp": 0.9132914338919925
        },
        "2015": {
          "rmse": 2.8613981043444165,
          "crps": 1.2061111106485032,
          "picp": 0.8796554934823091
        },
        "2016": {
          "rmse": 2.44739634453399,
          "crps": 1.0386818980706105,
          "picp": 0.915041782729805
        }
      },
      "rmse_mean": 2.6109153757154644,
      "rmse_std": 0.15275515692932262
    }
  }
}