{
  "model": "qtransformer_multi",
  "method": "input_tau",
  "alpha": 0.1,
  "fit_on": [
    "clean",
    "clock_skew_1.0",
    "clock_skew_2.0",
    "clock_skew_4.0",
    "contextual_outlier_1.0",
    "contextual_outlier_2.0",
    "contextual_outlier_4.0",
    "drift_1.0",
    "drift_2.0",
    "drift_4.0",
    "fgsm_1.0",
    "fgsm_2.0",
    "fgsm_4.0",
    "flatline_1.0",
    "flatline_2.0",
    "flatline_4.0",
    "gap_imputation_1.0",
    "gap_imputation_2.0",
    "gap_imputation_4.0",
    "level_shift_1.0",
    "level_shift_2.0",
    "level_shift_4.0",
    "noise_burst_1.0",
    "noise_burst_2.0",
    "noise_burst_4.0",
    "point_spike_1.0",
    "point_spike_2.0",
    "point_spike_4.0"
  ],
  "params": {
    "n_features": 6,
    "regressor": "HistGradientBoostingRegressor"
  },
  "settings": {
    "clean": {
      "before": {
        "picp": 0.8986768802228412,
        "mpiw": 6.49100251094512,
        "mis": 8.605050339566715,
        "pinball": 0.46686468286658295,
        "rmse_median": 2.2052987426703727
      },
      "after": {
        "picp": 0.9562441968430826,
        "mpiw": 9.147476435434752,
        "mis": 9.986443752583696,
        "pinball": 0.49659159734652747,
        "rmse_median": 2.2052987426703727
      }
    },
    "clock_skew_1.0": {
      "before": {
        "picp": 0.841225626740947,
        "mpiw": 6.4484959904310735,
        "mis": 9.710569210780841,
        "pinball": 0.5155676977212573,
        "rmse_median": 2.363191499495479
      },
      "after": {
        "picp": 0.9227019498607242,
        "mpiw": 9.08851885483001,
        "mis": 10.190624441749202,
        "pinball": 0.5322495535180979,
        "rmse_median": 2.363191499495479
      }
    },
    "clock_skew_2.0": {
      "before": {
        "picp": 0.7631151346332404,
        "mpiw": 6.396282823663878,
        "mis": 12.869125954459518,
        "pinball": 0.6246839508025879,
        "rmse_median": 2.674942320878047
      },
      "after": {
        "picp": 0.8792943361188487,
        "mpiw": 9.946487539110898,
        "mis": 12.684987524164859,
        "pinball": 0.6340195389810557,
        "rmse_median": 2.674942320878047
      }
    },
    "clock_skew_4.0": {
      "before": {
        "picp": 0.6642293407613742,
        "mpiw": 6.243796791177663,
        "mis": 19.971063618687026,
        "pinball": 0.8417524257463261,
        "rmse_median": 3.2766778148204727
      },
      "after": {
        "picp": 0.8226555246053854,
        "mpiw": 12.029859847907167,
        "mis": 18.172151747258297,
        "pinball": 0.8429769246872757,
        "rmse_median": 3.2766778148204727
      }
    },
    "contextual_outlier_1.0": {
      "before": {
        "picp": 0.8994893221912721,
        "mpiw": 6.490364294843892,
        "mis": 8.60185402695461,
        "pinball": 0.4667948536589378,
        "rmse_median": 2.205132686520122
      },
      "after": {
        "picp": 0.9571727019498607,
        "mpiw": 9.133921505270179,
        "mis": 9.994018541414684,
        "pinball": 0.49669817066844085,
        "rmse_median": 2.205132686520122
      }
    },
    "contextual_outlier_2.0": {
      "before": {
        "picp": 0.9000696378830083,
        "mpiw": 6.489117003933148,
        "mis": 8.600866083066927,
        "pinball": 0.4668514050962394,
        "rmse_median": 2.204753028792516
      },
      "after": {
        "picp": 0.9585654596100278,
        "mpiw": 9.159755292228448,
        "mis": 9.96452138007628,
        "pinball": 0.49660070944605794,
        "rmse_median": 2.204753028792516
      }
    },
    "contextual_outlier_4.0": {
      "before": {
        "picp": 0.9003017641597029,
        "mpiw": 6.48770748011995,
        "mis": 8.640712126644322,
        "pinball": 0.4675175703024173,
        "rmse_median": 2.206514332711958
      },
      "after": {
        "picp": 0.9590297121634169,
        "mpiw": 9.375526374871404,
        "mis": 10.190183317040464,
        "pinball": 0.5022112711348299,
        "rmse_median": 2.206514332711958
      }
    },
    "drift_1.0": {
      "before": {
        "picp": 0.7464020427112349,
        "mpiw": 6.496647944866894,
        "mis": 11.926266341083158,
        "pinball": 0.6146784480867665,
        "rmse_median": 2.6156150681504533
      },
      "after": {
        "picp": 0.8791782729805014,
        "mpiw": 9.805582597716107,
        "mis": 11.921444818892052,
        "pinball": 0.621731378938044,
        "rmse_median": 2.6156150681504533
      }
    },
    "drift_2.0": {
      "before": {
        "picp": 0.5558263695450325,
        "mpiw": 6.530661219143237,
        "mis": 21.994533997839824,
        "pinball": 0.9565647881406443,
        "rmse_median": 3.5430866213699015
      },
      "after": {
        "picp": 0.7744893221912721,
        "mpiw": 12.152271752772215,
        "mis": 18.189503750803233,
        "pinball": 0.9125498078888938,
        "rmse_median": 3.5430866213699015
      }
    },
    "drift_4.0": {
      "before": {
        "picp": 0.30779944289693595,
        "mpiw": 6.709061052379753,
        "mis": 55.01315243938459,
        "pinball": 1.9368345061549486,
        "rmse_median": 6.024711666650385
      },
      "after": {
        "picp": 0.7260909935004642,
        "mpiw": 19.241669484542413,
        "mis": 32.32644240203773,
        "pinball": 1.588207205339994,
        "rmse_median": 6.024711666650385
      }
    },
    "fgsm_1.0": {
      "before": {
        "picp": 0.49396471680594245,
        "mpiw": 6.503648022213402,
        "mis": 22.35297638412007,
        "pinball": 1.0389658968837336,
        "rmse_median": 3.947328736524157
      },
      "after": {
        "picp": 0.8474930362116991,
        "mpiw": 12.004706454672398,
        "mis": 15.414173528579875,
        "pinball": 0.9004622680623477,
        "rmse_median": 3.947328736524157
      }
    },
    "fgsm_2.0": {
      "before": {
        "picp": 0.3059424326833798,
        "mpiw": 6.5626108563356915,
        "mis": 41.01444140152956,
        "pinball": 1.5864083073093338,
        "rmse_median": 5.202499815547417
      },
      "after": {
        "picp": 0.8232358402971216,
        "mpiw": 16.477001798310084,
        "mis": 21.14411976763916,
        "pinball": 1.2409267272351194,
        "rmse_median": 5.202499815547417
      }
    },
    "fgsm_4.0": {
      "before": {
        "picp": 0.1888347260909935,
        "mpiw": 6.813202389462789,
        "mis": 79.46728744507641,
        "pinball": 2.618511602584275,
        "rmse_median": 7.568495830871667
      },
      "after": {
        "picp": 0.8284586815227484,
        "mpiw": 26.01380800524988,
        "mis": 32.4917417224662,
        "pinball": 1.8682066280630285,
        "rmse_median": 7.568495830871667
      }
    },
    "flatline_1.0": {
      "before": {
        "picp": 0.6988161559888579,
        "mpiw": 6.451788571304592,
        "mis": 17.146382589532042,
        "pinball": 0.7647036696412718,
        "rmse_median": 3.0669158775948695
      },
      "after": {
        "picp": 0.8897400185701021,
        "mpiw": 12.759510124672042,
        "mis": 15.734020145237638,
        "pinball": 0.7684839754563576,
        "rmse_median": 3.0669158775948695
      }
    },
    "flatline_2.0": {
      "before": {
        "picp": 0.6980037140204272,
        "mpiw": 6.401009475165303,
        "mis": 16.20468409622641,
        "pinball": 0.7433709932881101,
        "rmse_median": 2.995939781819276
      },
      "after": {
        "picp": 0.8732590529247911,
        "mpiw": 11.60297760696354,
        "mis": 14.942755533932205,
        "pinball": 0.7412485068238232,
        "rmse_median": 2.995939781819276
      }
    },
    "flatline_4.0": {
      "before": {
        "picp": 0.6666666666666666,
        "mpiw": 6.327690733721401,
        "mis": 18.3919782673124,
        "pinball": 0.8060794347214392,
        "rmse_median": 3.310003283486944
      },
      "after": {
        "picp": 0.8651346332404828,
        "mpiw": 10.602743006072338,
        "mis": 15.354926007692567,
        "pinball": 0.7634837472320862,
        "rmse_median": 3.310003283486944
      }
    },
    "gap_imputation_1.0": {
      "before": {
        "picp": 0.8997214484679665,
        "mpiw": 6.489196589833121,
        "mis": 8.585196803827175,
        "pinball": 0.46513881584793537,
        "rmse_median": 2.1956217952939014
      },
      "after": {
        "picp": 0.955547818012999,
        "mpiw": 9.122270873019612,
        "mis": 9.952809218177848,
        "pinball": 0.4947593741126085,
        "rmse_median": 2.1956217952939014
      }
    },
    "gap_imputation_2.0": {
      "before": {
        "picp": 0.8969359331476323,
        "mpiw": 6.483516808938184,
        "mis": 8.665817104651373,
        "pinball": 0.4688365052613896,
        "rmse_median": 2.2117048288183763
      },
      "after": {
        "picp": 0.9563602599814299,
        "mpiw": 9.122470790924014,
        "mis": 10.094812179359803,
        "pinball": 0.49933078110701246,
        "rmse_median": 2.2117048288183763
      }
    },
    "gap_imputation_4.0": {
      "before": {
        "picp": 0.8925255338904364,
        "mpiw": 6.485008068807488,
        "mis": 8.852709045589464,
        "pinball": 0.4751719558343967,
        "rmse_median": 2.241975246336806
      },
      "after": {
        "picp": 0.9517177344475395,
        "mpiw": 9.217211772943305,
        "mis": 10.366052606197373,
        "pinball": 0.5084284501269539,
        "rmse_median": 2.241975246336806
      }
    },
    "level_shift_1.0": {
      "before": {
        "picp": 0.7761142061281338,
        "mpiw": 6.487142055141214,
        "mis": 11.153912365425041,
        "pinball": 0.5801308949761131,
        "rmse_median": 2.4865480360444185
      },
      "after": {
        "picp": 0.887883008356546,
        "mpiw": 9.504812683468108,
        "mis": 11.528537542282447,
        "pinball": 0.5925642548240972,
        "rmse_median": 2.4865480360444185
      }
    },
    "level_shift_2.0": {
      "before": {
        "picp": 0.6086350974930362,
        "mpiw": 6.506217204616189,
        "mis": 19.8358900026837,
        "pinball": 0.8747004179293798,
        "rmse_median": 3.300207776565128
      },
      "after": {
        "picp": 0.7898096564531105,
        "mpiw": 11.570312067880105,
        "mis": 17.342183881655387,
        "pinball": 0.854838966358385,
        "rmse_median": 3.300207776565128
      }
    },
    "level_shift_4.0": {
      "before": {
        "picp": 0.36803621169916434,
        "mpiw": 6.651420064082923,
        "mis": 48.815377204262006,
        "pinball": 1.7440851932477286,
        "rmse_median": 5.610062060598982
      },
      "after": {
        "picp": 0.729108635097493,
        "mpiw": 18.03943951947436,
        "mis": 30.752459785018573,
        "pinball": 1.486311917772889,
        "rmse_median": 5.610062060598982
      }
    },
    "noise_burst_1.0": {
      "before": {
        "picp": 0.8987929433611885,
        "mpiw": 6.494122441845974,
        "mis": 8.629733045313953,
        "pinball": 0.4677271281454442,
        "rmse_median": 2.2062840806452546
      },
      "after": {
        "picp": 0.9535747446610956,
        "mpiw": 8.885531755389596,
        "mis": 9.840929352346084,
        "pinball": 0.4930419563040722,
        "rmse_median": 2.2062840806452546
      }
    },
    "noise_burst_2.0": {
      "before": {
        "picp": 0.8921773444753947,
        "mpiw": 6.501159999102111,
        "mis": 8.91713952719095,
        "pinball": 0.48044136093943823,
        "rmse_median": 2.265023061168701
      },
      "after": {
        "picp": 0.9396471680594243,
        "mpiw": 8.670220546018,
        "mis": 10.107650552545879,
        "pinball": 0.5043770826832163,
        "rmse_median": 2.265023061168701
      }
    },
    "noise_burst_4.0": {
      "before": {
        "picp": 0.8762766945218199,
        "mpiw": 6.498512913452798,
        "mis": 9.499217479428085,
        "pinball": 0.5036510976664009,
        "rmse_median": 2.3667224667693065
      },
      "after": {
        "picp": 0.924791086350975,
        "mpiw": 9.004622989857042,
        "mis": 10.924783346776934,
        "pinball": 0.5356384597494535,
        "rmse_median": 2.3667224667693065
      }
    },
    "point_spike_1.0": {
      "before": {
        "picp": 0.8987929433611885,
        "mpiw": 6.4915782419236585,
        "mis": 8.615161430513698,
        "pinball": 0.4673930736448645,
        "rmse_median": 2.2067094002702
      },
      "after": {
        "picp": 0.9556638811513464,
        "mpiw": 9.131418574185506,
        "mis": 9.98340094519948,
        "pinball": 0.4968734204049645,
        "rmse_median": 2.2067094002702
      }
    },
    "point_spike_2.0": {
      "before": {
        "picp": 0.8979805013927576,
        "mpiw": 6.492854804215968,
        "mis": 8.6439274166201,
        "pinball": 0.46875083609298324,
        "rmse_median": 2.2117918724407613
      },
      "after": {
        "picp": 0.955547818012999,
        "mpiw": 9.135966523641915,
        "mis": 9.980879149761929,
        "pinball": 0.49789684634373865,
        "rmse_median": 2.2117918724407613
      }
    },
    "point_spike_4.0": {
      "before": {
        "picp": 0.8971680594243269,
        "mpiw": 6.493973468875096,
        "mis": 8.729455871458516,
        "pinball": 0.472006230047803,
        "rmse_median": 2.2254465131083228
      },
      "after": {
        "picp": 0.9556638811513464,
        "mpiw": 9.194161329382716,
        "mis": 10.095189155348207,
        "pinball": 0.5017619496420781,
        "rmse_median": 2.2254465131083228
      }
    }
  }
}